lours/__init__.py
lours/cli/__init__.py
lours/cli/caipy_to_fiftyone.py
lours/dataset/__init__.py
lours/dataset/dataset.py
lours/dataset/indexing.py
lours/dataset/io/__init__.py
lours/dataset/io/caipy.py
lours/dataset/io/coco.py
lours/dataset/io/common.py
lours/dataset/io/crowd_human.py
lours/dataset/io/darknet.py
lours/dataset/io/images_folder.py
lours/dataset/io/mot.py
lours/dataset/io/parquet.py
lours/dataset/io/pascalvoc.py
lours/dataset/io/schema_util/__init__.py
lours/dataset/io/schema_util/default-schema.json
lours/dataset/io/schema_util/schema_util_functions.py
lours/dataset/merge.py
lours/dataset/remap_presets/__init__.py
lours/dataset/remap_presets/coco_to_pascalvoc.csv
lours/dataset/remap_presets/coco_to_supercategory.csv
lours/dataset/split/balanced_groups.py
lours/dataset/split/dataset_splitter.py
lours/dataset/split/disjoint_groups.py
lours/evaluation/__init__.py
lours/evaluation/detection/__init__.py
lours/evaluation/detection/crowd_detection_evaluator.py
lours/evaluation/detection/detection_evaluator.py
lours/evaluation/detection/detection_evaluator_base.py
lours/evaluation/detection/util.py
lours/evaluation/evaluator.py
lours/utils/__init__.py
lours/utils/annotations_appender.py
lours/utils/bbox_converter.py
lours/utils/column_booleanizer.py
lours/utils/dataframe_formatter.py
lours/utils/difftools.py
lours/utils/doc_utils.py
lours/utils/fiftyone_convert.py
lours/utils/grouper.py
lours/utils/label_map_merger.py
lours/utils/notebook_utils.py
lours/utils/parquet_saver.py
lours/utils/regression_testing.py
lours/utils/testing.py
lours-1.2.1.dist-info/LICENSE
lours-1.2.1.dist-info/METADATA
lours-1.2.1.dist-info/WHEEL
lours-1.2.1.dist-info/entry_points.txt
lours-1.2.1.dist-info/RECORD
