Metadata-Version: 2.3
Name: lours
Version: 1.2.1
Summary: 
License: MIT
Author: XXII
Requires-Python: >=3.10,<3.14
Classifier: License :: OSI Approved :: MIT License
Classifier: Programming Language :: Python :: 3
Classifier: Programming Language :: Python :: 3.10
Classifier: Programming Language :: Python :: 3.11
Classifier: Programming Language :: Python :: 3.12
Classifier: Programming Language :: Python :: 3.13
Provides-Extra: fiftyone
Provides-Extra: plot-utils
Provides-Extra: regression
Requires-Dist: POT (>=0.9.1,<0.10.0)
Requires-Dist: PyYAML (>=6.0.1,<7.0.0)
Requires-Dist: boto3 (==1.26.83) ; extra == "fiftyone"
Requires-Dist: faker (>30)
Requires-Dist: fiftyone (>=1.0.0,<2.0.0) ; extra == "fiftyone"
Requires-Dist: imageio (>=2.31.3,<3.0.0)
Requires-Dist: imagesize (>=1.4.1,<2.0.0)
Requires-Dist: jsonschema-rs (>=0.29.0,<0.30.0)
Requires-Dist: networkx (>=3.4.2,<4.0.0)
Requires-Dist: pandas[parquet] (>=2,<3)
Requires-Dist: pytest-regressions (>=2.5.0,<3.0.0) ; extra == "regression"
Requires-Dist: requests (>=2,<3)
Requires-Dist: scikit-learn (>=1.3.0,<2.0.0)
Requires-Dist: shortuuid (>=1.0.11,<2.0.0)
Requires-Dist: toml (>=0.10.2,<0.11.0)
Requires-Dist: tqdm (>=4.64,<5.0)
Requires-Dist: typing-extensions (>=4.7.1,<5.0.0)
Requires-Dist: watchdog (>=6.0.0,<7.0.0)
Requires-Dist: xmltodict (>=0.14.0,<0.15.0)
